{"Receiving Leaders":
    [
        {
            "name": "Jerry Rice",
            "yards": 22895
        },
        {
            "name": "Larry Fitzgerald",
            "yards": 17492
        },
        {
            "name": "Terrell Owens",
            "yards": 15934
        },
        {
            "name": "Randy Moss",
            "yards": 15292
        },
        {
            "name": "Isaac Bruce",
            "yards": 15208
        },
        {
            "name": "Tony Gonzalez",
            "yards": 15127
        },
        {
            "name": "Tim Brown",
            "yards": 14934
        },
        {
            "name": "Steve Smith",
            "yards": 14731
        },
        {
            "name": "Marvin Harrison",
            "yards": 14580
        },
        {
            "name": "Reggie Wayne",
            "yards": 14345
        },
        {
            "name": "Andre Johnson",
            "yards": 14185
        },
        {
            "name": "James Lofton",
            "yards": 14004
        },
        {
            "name": "Cris Carter",
            "yards": 13899
        },
        {
            "name": "Anquan Boldin",
            "yards": 13779
        },
        {
            "name": "Henry Ellard",
            "yards": 13777
        },
        {
            "name": "Torry Holt",
            "yards": 13382
        },
        {
            "name": "Julio Jones",
            "yards": 13330
        },
        {
            "name": "Andre Reed",
            "yards": 13198
        },
        {
            "name": "Steve Largent",
            "yards": 13089
        },
        {
            "name": "Jason Witten",
            "yards": 13046
        },
        {
            "name": "Irving Fryar",
            "yards": 12785
        },
        {
            "name": "Art Monk",
            "yards": 12721
        },
        {
            "name": "Brandon Marshall",
            "yards": 12351
        },
        {
            "name": "Antonio Brown",
            "yards": 12291
        },
        {
            "name": "Jimmy Smith",
            "yards": 12287
        }
    ]
}